langbatch/__init__.py
langbatch/anthropic.py
langbatch/Batch.py
langbatch/batch_queues.py
langbatch/batch_storages.py
langbatch/BatchDispatcher.py
langbatch/BatchHandler.py
langbatch/bedrock.py
langbatch/bigquery_utils.py
langbatch/ChatCompletionBatch.py
langbatch/claude_utils.py
langbatch/EmbeddingBatch.py
langbatch/errors.py
langbatch/factory.py
langbatch/nova_utils.py
langbatch/openai.py
langbatch/record.proto
langbatch/record_llama.proto
langbatch/record_llama_pb2.py
langbatch/record_pb2.py
langbatch/request_queues.py
langbatch/schemas.py
langbatch/utils.py
langbatch/vertexai.py
langbatch-0.1.2.dist-info/LICENSE
langbatch-0.1.2.dist-info/METADATA
langbatch-0.1.2.dist-info/WHEEL
langbatch-0.1.2.dist-info/RECORD
