Metadata-Version: 2.1
Name: langbatch
Version: 0.1.2
Summary: LangBatch is a python package with unified API for AI batch processing workloads. Supports OpenAI, Anthropic, Azure OpenAI, Vertex AI
Home-page: https://pypi.org/project/langbatch/
License: Apache-2.0
Author: KarthikeyanVijayanEasyLLM
Author-email: karthikeyan.vijayan@easyllm.tech
Requires-Python: >=3.11,<4.0
Classifier: License :: OSI Approved :: Apache Software License
Classifier: Programming Language :: Python :: 3
Classifier: Programming Language :: Python :: 3.11
Classifier: Programming Language :: Python :: 3.12
Provides-Extra: all
Provides-Extra: anthropic
Provides-Extra: bedrock
Provides-Extra: redis
Provides-Extra: vertexai
Requires-Dist: anthropic (>=0.36.1,<0.37.0) ; extra == "anthropic" or extra == "all"
Requires-Dist: boto3 (>=1.36.16,<2.0.0) ; extra == "bedrock" or extra == "all"
Requires-Dist: fastavro (>=1.9.7,<2.0.0) ; extra == "vertexai" or extra == "all"
Requires-Dist: google-cloud-aiplatform (>=1.65.0,<2.0.0) ; extra == "vertexai" or extra == "all"
Requires-Dist: google-cloud-bigquery-storage (==2.26.0) ; extra == "vertexai" or extra == "all"
Requires-Dist: jsonlines (>=4.0.0,<5.0.0)
Requires-Dist: openai (>=1.43.0,<2.0.0)
Requires-Dist: redis (>=5.0.8,<6.0.0) ; extra == "redis" or extra == "all"
Project-URL: Documentation, https://github.com/EasyLLM/langbatch/blob/main/README.md
Project-URL: Repository, https://github.com/EasyLLM/langbatch
